autoboy/__init__.py
autoboy/main.py
autoboy-1.0.33.dist-info/LICENSE
autoboy-1.0.33.dist-info/METADATA
autoboy-1.0.33.dist-info/WHEEL
autoboy-1.0.33.dist-info/top_level.txt
autoboy-1.0.33.dist-info/zip-safe
autoboy-1.0.33.dist-info/RECORD
